{"frames":{"00000.png":{"frame":{"h":191,"idx":0,"w":283,"x":0,"y":0},"sourceSize":{"h":600,"w":800},"spriteSourceSize":{"x":248,"y":274}},"00001.png":{"frame":{"h":184,"idx":0,"w":279,"x":0,"y":192},"sourceSize":{"h":600,"w":800},"spriteSourceSize":{"x":253,"y":277}},"00002.png":{"frame":{"h":173,"idx":0,"w":271,"x":284,"y":0},"sourceSize":{"h":600,"w":800},"spriteSourceSize":{"x":256,"y":285}},"00003.png":{"frame":{"h":161,"idx":0,"w":256,"x":0,"y":377},"sourceSize":{"h":600,"w":800},"spriteSourceSize":{"x":267,"y":294}},"00004.png":{"frame":{"h":163,"idx":0,"w":190,"x":556,"y":0},"sourceSize":{"h":600,"w":800},"spriteSourceSize":{"x":304,"y":292}},"00005.png":{"frame":{"h":172,"idx":0,"w":172,"x":0,"y":539},"sourceSize":{"h":600,"w":800},"spriteSourceSize":{"x":308,"y":284}},"00006.png":{"frame":{"h":193,"idx":0,"w":218,"x":747,"y":0},"sourceSize":{"h":600,"w":800},"spriteSourceSize":{"x":296,"y":272}},"00007.png":{"frame":{"h":251,"idx":0,"w":255,"x":284,"y":174},"sourceSize":{"h":600,"w":800},"spriteSourceSize":{"x":273,"y":243}},"00008.png":{"frame":{"h":210,"idx":0,"w":281,"x":0,"y":712},"sourceSize":{"h":600,"w":800},"spriteSourceSize":{"x":267,"y":264}},"00009.png":{"frame":{"h":234,"idx":0,"w":347,"x":540,"y":194},"sourceSize":{"h":600,"w":800},"spriteSourceSize":{"x":234,"y":252}},"00010.png":{"frame":{"h":220,"idx":0,"w":359,"x":257,"y":429},"sourceSize":{"h":600,"w":800},"spriteSourceSize":{"x":213,"y":267}},"00011.png":{"frame":{"h":227,"idx":0,"w":366,"x":282,"y":650},"sourceSize":{"h":600,"w":800},"spriteSourceSize":{"x":220,"y":261}},"00012.png":{"frame":{"h":219,"idx":0,"w":373,"x":617,"y":429},"sourceSize":{"h":600,"w":800},"spriteSourceSize":{"x":215,"y":271}},"00013.png":{"frame":{"h":218,"idx":0,"w":364,"x":649,"y":649},"sourceSize":{"h":600,"w":800},"spriteSourceSize":{"x":226,"y":270}}},"meta":{"image":"petskill_17.png","prefix":"skill/petskill_17/"}}