{"frames":{"00034.png":{"frame":{"h":117,"idx":0,"w":101,"x":0,"y":0},"sourceSize":{"h":600,"w":800},"spriteSourceSize":{"x":345,"y":335}},"00035.png":{"frame":{"h":118,"idx":0,"w":106,"x":0,"y":118},"sourceSize":{"h":600,"w":800},"spriteSourceSize":{"x":346,"y":339}},"00036.png":{"frame":{"h":119,"idx":0,"w":108,"x":0,"y":237},"sourceSize":{"h":600,"w":800},"spriteSourceSize":{"x":349,"y":342}},"00037.png":{"frame":{"h":122,"idx":0,"w":110,"x":107,"y":0},"sourceSize":{"h":600,"w":800},"spriteSourceSize":{"x":350,"y":344}},"00038.png":{"frame":{"h":117,"idx":0,"w":114,"x":218,"y":0},"sourceSize":{"h":600,"w":800},"spriteSourceSize":{"x":346,"y":346}},"00039.png":{"frame":{"h":108,"idx":0,"w":116,"x":107,"y":123},"sourceSize":{"h":600,"w":800},"spriteSourceSize":{"x":343,"y":347}},"00040.png":{"frame":{"h":99,"idx":0,"w":111,"x":333,"y":0},"sourceSize":{"h":600,"w":800},"spriteSourceSize":{"x":346,"y":349}},"00041.png":{"frame":{"h":108,"idx":0,"w":103,"x":333,"y":100},"sourceSize":{"h":600,"w":800},"spriteSourceSize":{"x":351,"y":346}},"00042.png":{"frame":{"h":116,"idx":0,"w":100,"x":224,"y":118},"sourceSize":{"h":600,"w":800},"spriteSourceSize":{"x":351,"y":341}},"00043.png":{"frame":{"h":125,"idx":0,"w":97,"x":109,"y":232},"sourceSize":{"h":600,"w":800},"spriteSourceSize":{"x":349,"y":335}},"00044.png":{"frame":{"h":125,"idx":0,"w":97,"x":325,"y":209},"sourceSize":{"h":600,"w":800},"spriteSourceSize":{"x":348,"y":333}},"00045.png":{"frame":{"h":117,"idx":0,"w":99,"x":207,"y":235},"sourceSize":{"h":600,"w":800},"spriteSourceSize":{"x":346,"y":334}}},"meta":{"image":"runbei.png","prefix":"anim/pet_51/runbei/"}}